<?xml version="1.0" encoding="UTF-8" standalone="yes"?>
<portlet-definition xmlns="https://source.jasig.org/schemas/uportal/io/portlet-definition" xmlns:ns2="https://source.jasig.org/schemas/uportal" xmlns:ns3="https://source.jasig.org/schemas/uportal/io/portlet-type" xmlns:ns4="https://source.jasig.org/schemas/uportal/io/event-aggregation" xmlns:ns5="https://source.jasig.org/schemas/uportal/io/subscribed-fragment" xmlns:ns6="https://source.jasig.org/schemas/uportal/io/permission-owner" xmlns:ns7="https://source.jasig.org/schemas/uportal/io/user" xmlns:ns8="https://source.jasig.org/schemas/uportal/io/stylesheet-descriptor" xmlns:xsi="http://www.w3.org/2001/XMLSchema-instance" version="5.0" xsi:schemaLocation="https://source.jasig.org/schemas/uportal/io/portlet-definition https://source.jasig.org/schemas/uportal/io/portlet-definition/portlet-definition-5.0.xsd">
    <title>Update Emergency Contact Info</title>
    <name>Update Emergency Contact Info</name>
    <fname>cpp-update-emergency-contact-info</fname>
    <type>Advanced CMS</type>
    <timeout>5000</timeout>
    <portlet-descriptor>
        <ns2:webAppName>/SimpleContentPortlet</ns2:webAppName>
        <ns2:portletName>cms</ns2:portletName>
    </portlet-descriptor>
    <category>Administration</category>
    <group>Portal Administrators</group>
    <parameter>
        <name>alternate</name>
        <value>false</value>
    </parameter>
    <parameter>
        <name>blockImpersonation</name>
        <value>false</value>
    </parameter>
    <parameter>
        <name>chromeStyle</name>
        <value>default</value>
    </parameter>
    <parameter>
        <name>configurable</name>
        <value>false</value>
    </parameter>
    <parameter>
        <name>disableDynamicTitle</name>
        <value>true</value>
    </parameter>
    <parameter>
        <name>editable</name>
        <value>false</value>
    </parameter>
    <parameter>
        <name>hasAbout</name>
        <value>false</value>
    </parameter>
    <parameter>
        <name>hasHelp</name>
        <value>false</value>
    </parameter>
    <parameter>
        <name>hideFromMobile</name>
        <value>false</value>
    </parameter>
    <parameter>
        <name>highlight</name>
        <value>false</value>
    </parameter>
    <parameter>
        <name>printable</name>
        <value>false</value>
    </parameter>
    <parameter>
        <name>showChrome</name>
        <value>true</value>
    </parameter>
    <portlet-preference>
        <name>cleanContent</name>
        <readOnly>false</readOnly>
        <value>false</value>
    </portlet-preference>
    <portlet-preference>
        <name>content</name>
        <readOnly>false</readOnly>
        <value>
            <![CDATA[
				<div class="page-container">
					<div class="">
				   		<div class="portlet-alert" >    
				   			<div class="container-fluid" >
								<table style="border-style: solid; border-color:#7C1D20;">
									<tr>
										<th><span style="vertical-align: middle;" class="fa fa-exclamation-triangle fa-fw"></span>&nbsp;Action Required!</th>
									</tr>
								</table>
							</div>
						</div>
					</div>
				</div>
				<div style="font-size:12px;">
					<p><strong>A registration hold will be placed on your record on Dec. 1, 2014 if you do not validate/update your Emergency Contact Info by Nov. 26.</strong></p>
                	<div class="well well-sm blurb">
						Cal Poly Pomona is committed to ensuring student safety and well-being.  The University requires you to review and validate your Emergency Contact Information in BroncoDirect on an annual basis.   To do this, access your <a style="text-decoration: underline;" href="https://auth.cpp.edu/cas?service=https://cms.cms.csupomona.edu/psp/HPOMPRDF/EMPLOYEE/HRMS/c/CC_PORTFOLIO.SS_CC_EMERG_CNTCT.GBL?PORTALPARAM_PTCNAV=HC_SS_CC_EMERG_CNTCT_GBL&EOPP.SCNode=HRMS&EOPP.SCPortal=EMPLOYEE&EOPP.SCName=CO_EMPLOYEE_SELF_SERVICE&EOPP.SCLabel=Campus%20Personal%20Information&EOPP.SCFName=HCCC_PERS_PORTFOLIO&EOPP.SCSecondary=true&EOPP.SCPTfname=HCCC_PERS_PORTFOLIO&FolderPath=PORTAL_ROOT_OBJECT.CO_EMPLOYEE_SELF_SERVICE.HCCC_PERS_PORTFOLIO.HC_SS_CC_EMERG_CNTCT_GBL&IsFolder=false?cmd=start&amp;languageCd=ENG&amp;userid=PS&amp;pwd=z&amp;calstateEduPersonEmplID" target="_blank">Emergency Contact Information</a> page in BroncoDirect and review/update your information.  <u>Even if you don’t make changes, you must click on the UPDATE button.</u>  Need some help?  View the <a href="http://public.dsa.cpp.edu/registrar/public/GuideEmergencyContact.pdf">Guide To Update Your Emergency Info for detailed instructions</a> (PDF).</p>
					</div>
				</div>
            ]]>
		</value>
    </portlet-preference>
</portlet-definition>
